common/__init__.py
common/constants.py
common/models.py
common/utils.py
wheelio_assesement_common-0.1.0.dist-info/METADATA
wheelio_assesement_common-0.1.0.dist-info/WHEEL
wheelio_assesement_common-0.1.0.dist-info/top_level.txt
wheelio_assesement_common-0.1.0.dist-info/RECORD
