Metadata-Version: 2.1
Name: wheelio-assesement-common
Version: 0.1.0
Summary: A common package for shared utilities and models for wheel.io technical challenge
Home-page: https://github.com/yourusername/common_package
Author: Ashwin Singh
Author-email: ashwinsinghgr8@gmail.com
Classifier: Programming Language :: Python :: 3
Classifier: License :: OSI Approved :: MIT License
Classifier: Operating System :: OS Independent
Requires-Python: >=3.11
Requires-Dist: pydantic
Requires-Dist: beanie
Requires-Dist: pyjwt
Requires-Dist: fastapi
Requires-Dist: motor
